LICENSE
MANIFEST.in
README.md
setup.py
nosqlmodel/__init__.py
nosqlmodel/basenosql.py
nosqlmodel.egg-info/PKG-INFO
nosqlmodel.egg-info/SOURCES.txt
nosqlmodel.egg-info/dependency_links.txt
nosqlmodel.egg-info/requires.txt
nosqlmodel.egg-info/top_level.txt
nosqlmodel/connectors/__init__.py
nosqlmodel/connectors/baseconnector.py
nosqlmodel/connectors/dynamoconnector.py
nosqlmodel/connectors/redisconnector.py